rchl_websocket/__init__.py
rchl_websocket/client.py
rchl_websocket-0.1.4.dist-info/WHEEL
rchl_websocket-0.1.4.dist-info/METADATA
rchl_websocket-0.1.4.dist-info/RECORD
